mahdi/__init__.py
RNDMMAHDICK-0.3.dist-info/METADATA
RNDMMAHDICK-0.3.dist-info/WHEEL
RNDMMAHDICK-0.3.dist-info/top_level.txt
RNDMMAHDICK-0.3.dist-info/RECORD
